{
    "openapi": "3.0.0",
    "info": {
        "version": "1.0.0",
        "title": "E-commerce API",
        "description": "API for E-commerce Application"
    },
    "servers": [
        {
            "url": "http://localhost:3200",
            "description": "Local server"
        }
    ],
    "components": {
        "securitySchemes": {
            "JWT": {
                "in": "header",
                "type": "apiKey",
                "name": "Authorization"
            }
        }
    },
    "paths": {
        "/api/users/signup": {
            "post": {
                "tags": [
                    "Users"
                ],
                "summary": "User Signup",
                "description": "Endpoint for user registration",
                "requestBody": {
                    "content": {
                        "application/json": {
                            "schema": {
                                "type": "object",
                                "properties": {
                                    "username": {
                                        "type": "string"
                                    },
                                    "email": {
                                        "type": "string"
                                    },
                                    "password": {
                                        "type": "string"
                                    },
                                    "type": {
                                        "type": "string",
                                        "enum": [
                                            "customer",
                                            "seller"
                                        ],
                                        "default": "customer"
                                    }
                                },
                                "required": [
                                    "username",
                                    "email",
                                    "password"
                                ]
                            }
                        }
                    }
                },
                "required": true,
                "responses": {
                    "201": {
                        "description": "User created successfully"
                    },
                    "400": {
                        "description": "User registration failed"
                    }
                }
            }
        },
        "/api/users/signIn": {
            "post": {
                "tags": [
                    "Users"
                ],
                "summary": "User SignIn",
                "description": "Endpoint for user login",
                "requestBody": {
                    "content": {
                        "application/json": {
                            "schema": {
                                "type": "object",
                                "properties": {
                                    "email": {
                                        "type": "string"
                                    },
                                    "password": {
                                        "type": "string"
                                    }
                                },
                                "required": [
                                    "email",
                                    "password"
                                ]
                            }
                        }
                    },
                    "required": true
                },
                "responses": {
                    "200": {
                        "description": "User logged in successfully"
                    },
                    "401": {
                        "description": "Invalid email or password"
                    }
                }
            }
        },
        "/api/product": {
            "get": {
                "tags": [
                    "Products"
                ],
                "summary": "Get Products",
                "description": "Endpoint to retrieve all products",
                "security": [
                    {
                        "JWT": {}
                    }
                ],
                "responses": {
                    "200": {
                        "description": "A list of products",
                        "schema": {
                            "type": "array",
                            "items": {
                                "type": "object",
                                "properties": {
                                    "id": {
                                        "type": "string"
                                    },
                                    "name": {
                                        "type": "string"
                                    },
                                    "price": {
                                        "type": "number"
                                    },
                                    "description": {
                                        "type": "string"
                                    }
                                }
                            }
                        }
                    }
                }
            }
        }
    }
}